nuber-1.1.1.dist-info/METADATA
nuber-1.1.1.dist-info/WHEEL
nuber-1.1.1.dist-info/entry_points.txt
nuber/__init__.py
nuber/bookmarks.py
nuber/config.py
nuber/toc.py
nuber/listview.py
nuber/cmdline.py
nuber/reader.py
nuber/rust_module/__init__.py
nuber/rust_module/nuber.cpython-38-i386-linux-gnu.so
nuber-1.1.1.dist-info/RECORD
