Metadata-Version: 2.1
Name: nuber
Version: 1.1.1
Requires-Dist: ueberzug>=18.1.9
Requires-Dist: appdirs>=1.4.4
Requires-Dist: click>=8.0.1
Author: Moshe Sherman <moshesher1998@gmail.com>
Author-email: Moshe Sherman <moshesher1998@gmail.com>
